pyzeebe/__init__.py
pyzeebe/py.typed
pyzeebe/types.py
pyzeebe/channel/__init__.py
pyzeebe/channel/channel_options.py
pyzeebe/channel/insecure_channel.py
pyzeebe/channel/oauth_channel.py
pyzeebe/channel/secure_channel.py
pyzeebe/channel/utils.py
pyzeebe/client/__init__.py
pyzeebe/client/client.py
pyzeebe/client/sync_client.py
pyzeebe/credentials/__init__.py
pyzeebe/credentials/oauth.py
pyzeebe/errors/__init__.py
pyzeebe/errors/credentials_errors.py
pyzeebe/errors/job_errors.py
pyzeebe/errors/message_errors.py
pyzeebe/errors/process_errors.py
pyzeebe/errors/pyzeebe_errors.py
pyzeebe/errors/zeebe_errors.py
pyzeebe/function_tools/__init__.py
pyzeebe/function_tools/async_tools.py
pyzeebe/function_tools/dict_tools.py
pyzeebe/function_tools/parameter_tools.py
pyzeebe/grpc_internals/__init__.py
pyzeebe/grpc_internals/grpc_utils.py
pyzeebe/grpc_internals/types.py
pyzeebe/grpc_internals/zeebe_adapter.py
pyzeebe/grpc_internals/zeebe_adapter_base.py
pyzeebe/grpc_internals/zeebe_cluster_adapter.py
pyzeebe/grpc_internals/zeebe_job_adapter.py
pyzeebe/grpc_internals/zeebe_message_adapter.py
pyzeebe/grpc_internals/zeebe_process_adapter.py
pyzeebe/job/__init__.py
pyzeebe/job/job.py
pyzeebe/job/job_status.py
pyzeebe/proto/__init__.py
pyzeebe/proto/gateway_pb2.py
pyzeebe/proto/gateway_pb2.pyi
pyzeebe/proto/gateway_pb2_grpc.py
pyzeebe/proto/gateway_pb2_grpc.pyi
pyzeebe/task/__init__.py
pyzeebe/task/exception_handler.py
pyzeebe/task/task.py
pyzeebe/task/task_builder.py
pyzeebe/task/task_config.py
pyzeebe/task/types.py
pyzeebe/worker/__init__.py
pyzeebe/worker/job_executor.py
pyzeebe/worker/job_poller.py
pyzeebe/worker/task_router.py
pyzeebe/worker/task_state.py
pyzeebe/worker/worker.py
pyzeebe-4.7.0.dist-info/METADATA
pyzeebe-4.7.0.dist-info/WHEEL
pyzeebe-4.7.0.dist-info/licenses/LICENSE.md
pyzeebe-4.7.0.dist-info/RECORD
