Metadata-Version: 2.4
Name: pyzeebe
Version: 4.7.0
Summary: Zeebe client api
Project-URL: homepage, https://github.com/camunda-community-hub/pyzeebe
Project-URL: repository, https://github.com/camunda-community-hub/pyzeebe
Project-URL: documentation, https://camunda-community-hub.github.io/pyzeebe/
Author-email: Jonatan Martens <jonatanmartenstav@gmail.com>
Maintainer-email: Dmitriy <dimastbk@proton.me>
License-Expression: MIT
License-File: LICENSE.md
Keywords: workflow,workflow-engine,zeebe
Classifier: License :: OSI Approved :: MIT License
Classifier: Operating System :: OS Independent
Classifier: Programming Language :: Python :: 3
Requires-Python: >=3.9
Requires-Dist: anyio>=4.6.0
Requires-Dist: grpcio-health-checking>=1.66
Requires-Dist: grpcio>=1.66
Requires-Dist: oauthlib>=3.1.0
Requires-Dist: protobuf<7.0,>=5.28
Requires-Dist: requests-oauthlib<3.0.0,>=1.3.0
Requires-Dist: typing-extensions>=4.11.0
